sqs_handler/__init__.py
sqs_handler/sqs_handler.py
sqs_handler-0.1.0.dist-info/LICENSE
sqs_handler-0.1.0.dist-info/METADATA
sqs_handler-0.1.0.dist-info/WHEEL
sqs_handler-0.1.0.dist-info/top_level.txt
sqs_handler-0.1.0.dist-info/RECORD
